{
  "doc_type": "lk_supreme_court_judgements",
  "doc_id": "2021-11-03-SC-APPEAL-45-2014",
  "num": "SC/APPEAL/45/2014",
  "date_str": "2021-11-03",
  "description": "",
  "url_pdf": "https://supremecourt.lk/wp-content/uploads/judgements/sc_appeal_45_2014.pdf",
  "url_metadata": "https://supremecourt.lk/judgements/",
  "parties": "Gardihewa Kodikara Mallika Ratnapremi Fonseka No. 380B, Preeethipura, Kalalgoda, Pannipitya Applicant Vs. Sri Lanka Insurance Corporation Limited, No. 21, Vauxhall Street, Colombo 02. Respondent AND BETWEEN Sri Lanka Insurance Corporation Limited, No. 21, Vauxhall Street, Colombo 02. Respondent-Appellant Vs. Gardihewa Kodikara Mallika Ratnapremi Fonseka No. 380B, Preeethipura, Kalalgoda, Pannipitya Applicant-Respondent AND NOW BETWEEN Sri Lanka Insurance Corporation Limited, No. 21, Vauxhall Street, Colombo 02. Respondent-Appellant-Appellant Vs. Gardihewa Kodikara Mallika Ratnapremi Fonseka No. 380B, Preeethipura, Kalalgoda, Pannipitya Applicant-Respondent-Respondent",
  "judgement_by": "Hon. Buwaneka Aluwihare PC, J"
}