{
  "doc_type": "lk_supreme_court_judgements",
  "doc_id": "2026-03-31-SC-CHC-APPEAL-20-2012",
  "num": "SC/CHC APPEAL/20/2012",
  "date_str": "2026-03-31",
  "description": "Hon. Mahinda Samayawardhena J - Ceylon Paper Sacks (Private) ...",
  "url_metadata": "https://supremecourt.lk/judgements/",
  "lang": "en",
  "url_pdf": "https://supremecourt.lk/wp-content/uploads/judgements/sc_chc_appeal_20_2012.pdf",
  "parties": "Ceylon Paper Sacks (Private) Limited, No. 47, Maligawa Road, Etul Kotte. Defendant-Appellant Vs. Michael Laurents Cyrille Caderamanpulle, No. 15/5, Victoria Place, Elvitigala Mawatha, Colombo 08. (Deceased) Joseph Romesh Shehan Caderamanpulle, No. 33, Boran Road, Cofield, Victoria 3162, Australia. Substituted Plaintiff-Respondent\n\nView More",
  "judgement_by": "Hon. Mahinda Samayawardhena J"
}